.gitignore
CHANGES.txt
README.rst
development.ini
setup.cfg
setup.py
kotti_wysihtml5/__init__.py
kotti_wysihtml5.egg-info/PKG-INFO
kotti_wysihtml5.egg-info/SOURCES.txt
kotti_wysihtml5.egg-info/dependency_links.txt
kotti_wysihtml5.egg-info/entry_points.txt
kotti_wysihtml5.egg-info/not-zip-safe
kotti_wysihtml5.egg-info/requires.txt
kotti_wysihtml5.egg-info/top_level.txt
kotti_wysihtml5/templates/deform/richtext.pt
kotti_wysihtml5/tests/conftest.py
kotti_wysihtml5/tests/test_configure.py