Metadata-Version: 1.1
Name: kotti-wysihtml5
Version: 0.1.1
Summary: wysihtml5 for Kotti
Home-page: https://github.com/teixas/kotti_wysihtml5
Author: Nuno Teixeira
Author-email: teixas@gmail.com
License: BSD
Keywords: wysihtml5 bootstrap image browser kotti cms pylons pyramid
Platform: UNKNOWN
Classifier: Programming Language :: Python
Classifier: Framework :: Pylons
Classifier: Topic :: Internet :: WWW/HTTP
Classifier: Topic :: Internet :: WWW/HTTP :: Dynamic Content
Classifier: Topic :: Internet :: WWW/HTTP :: WSGI :: Application
Classifier: License :: OSI Approved :: MIT License
